rigel_registry_plugin/__init__.py
rigel_registry_plugin/exceptions.py
rigel_registry_plugin/plugin.py
rigel_registry_plugin/registries/__init__.py
rigel_registry_plugin/registries/ecr.py
rigel_registry_plugin/registries/generic.py
rigel_registry_plugin-0.1.6.dist-info/LICENSE.md
rigel_registry_plugin-0.1.6.dist-info/WHEEL
rigel_registry_plugin-0.1.6.dist-info/METADATA
rigel_registry_plugin-0.1.6.dist-info/RECORD
